odoo8_addon_medical_insurance_us-8.0.1.1.0.99.dev7-py2.7-nspkg.pth
odoo8_addon_medical_insurance_us-8.0.1.1.0.99.dev7.dist-info/DESCRIPTION.rst
odoo8_addon_medical_insurance_us-8.0.1.1.0.99.dev7.dist-info/METADATA
odoo8_addon_medical_insurance_us-8.0.1.1.0.99.dev7.dist-info/RECORD
odoo8_addon_medical_insurance_us-8.0.1.1.0.99.dev7.dist-info/WHEEL
odoo8_addon_medical_insurance_us-8.0.1.1.0.99.dev7.dist-info/metadata.json
odoo8_addon_medical_insurance_us-8.0.1.1.0.99.dev7.dist-info/namespace_packages.txt
odoo8_addon_medical_insurance_us-8.0.1.1.0.99.dev7.dist-info/top_level.txt
odoo_addons/medical_insurance_us/README.rst
odoo_addons/medical_insurance_us/__init__.py
odoo_addons/medical_insurance_us/__openerp__.py
odoo_addons/medical_insurance_us/i18n/pt_BR.po
odoo_addons/medical_insurance_us/models/__init__.py
odoo_addons/medical_insurance_us/models/medical_insurance_plan.py
odoo_addons/medical_insurance_us/models/medical_insurance_template.py
odoo_addons/medical_insurance_us/tests/medical_insurance_plan.yml
odoo_addons/medical_insurance_us/tests/medical_insurance_template.yml
odoo_addons/medical_insurance_us/views/medical_insurance_plan_view.xml
odoo_addons/medical_insurance_us/views/medical_insurance_template_view.xml
